streamlit_pills/__init__.py
streamlit_pills/frontend/.env
streamlit_pills/frontend/.prettierrc
streamlit_pills/frontend/build/asset-manifest.json
streamlit_pills/frontend/build/index.html
streamlit_pills/frontend/build/precache-manifest.9d92b1bae74866bbe3741586b64f0937.js
streamlit_pills/frontend/build/service-worker.js
streamlit_pills/frontend/build/static/js/2.d3d25e35.chunk.js
streamlit_pills/frontend/build/static/js/2.d3d25e35.chunk.js.LICENSE.txt
streamlit_pills/frontend/build/static/js/2.d3d25e35.chunk.js.map
streamlit_pills/frontend/build/static/js/main.8d37031a.chunk.js
streamlit_pills/frontend/build/static/js/main.8d37031a.chunk.js.map
streamlit_pills/frontend/build/static/js/runtime-main.683ff83b.js
streamlit_pills/frontend/build/static/js/runtime-main.683ff83b.js.map
streamlit_pills/frontend/build/styles.css
streamlit_pills/frontend/package-lock.json
streamlit_pills/frontend/package.json
streamlit_pills/frontend/public/index.html
streamlit_pills/frontend/public/styles.css
streamlit_pills/frontend/src/index.tsx
streamlit_pills/frontend/src/react-app-env.d.ts
streamlit_pills/frontend/tsconfig.json
streamlit_pills-0.2.0.dist-info/LICENSE
streamlit_pills-0.2.0.dist-info/WHEEL
streamlit_pills-0.2.0.dist-info/METADATA
streamlit_pills-0.2.0.dist-info/RECORD
